ogip/__init__.py
ogip/cli.py
ogip/core.py
ogip/spec.py
ogip/tools.py
ogip-0.2.1.dist-info/COPYING
ogip-0.2.1.dist-info/METADATA
ogip-0.2.1.dist-info/WHEEL
ogip-0.2.1.dist-info/entry_points.txt
ogip-0.2.1.dist-info/top_level.txt
ogip-0.2.1.dist-info/RECORD
