Metadata-Version: 2.1
Name: ogip
Version: 0.2.1
Summary: ogip
Home-page: https://odahub.io/
Author: V.S.
Author-email: vladimir.savchenko@gmail.com
License: GPL-2+
Platform: UNKNOWN
Classifier: Development Status :: 4 - Beta
Classifier: Environment :: Console
Classifier: Intended Audience :: Science/Research
Classifier: License :: OSI Approved :: GNU General Public License v2 or later (GPLv2+)
Classifier: Operating System :: POSIX
Classifier: Programming Language :: Python :: 3.5
Classifier: Programming Language :: Python :: 3.6
Classifier: Programming Language :: Python :: 3.7
Classifier: Programming Language :: Python :: 3.8
Classifier: Topic :: Internet
Classifier: Topic :: Scientific/Engineering :: Astronomy
License-File: COPYING
Requires-Dist: numpy (>=1.16.0)
Requires-Dist: astropy
Requires-Dist: scipy
Requires-Dist: click
Provides-Extra: plot
Requires-Dist: matplotlib ; extra == 'plot'
Provides-Extra: testing
Requires-Dist: pytest (>=4.6) ; extra == 'testing'
Requires-Dist: mypy ; extra == 'testing'
Requires-Dist: pylint ; extra == 'testing'
